<annotation>
	<folder>tlrr</folder>
	<filename>001692.JPG</filename>
	<path>C:\Users\NEAR6\Desktop\tlrr\001692.JPG</path>
	<source>
		<database>Unknown</database>
	</source>
	<size>
		<width>937</width>
		<height>861</height>
		<depth>3</depth>
	</size>
	<segmented>0</segmented>
	<object>
		<name>Traffic_light_red</name>
		<pose>Unspecified</pose>
		<truncated>0</truncated>
		<difficult>0</difficult>
		<bndbox>
			<xmin>332</xmin>
			<ymin>91</ymin>
			<xmax>437</xmax>
			<ymax>128</ymax>
		</bndbox>
	</object>
</annotation>
