<annotation>
	<folder>110r</folder>
	<filename>001299.jpg</filename>
	<path>C:\Users\NEAR6\Desktop\110r\001299.jpg</path>
	<source>
		<database>Unknown</database>
	</source>
	<size>
		<width>1200</width>
		<height>675</height>
		<depth>3</depth>
	</size>
	<segmented>0</segmented>
	<object>
		<name>Speed_limit_110km</name>
		<pose>Unspecified</pose>
		<truncated>0</truncated>
		<difficult>0</difficult>
		<bndbox>
			<xmin>14</xmin>
			<ymin>123</ymin>
			<xmax>255</xmax>
			<ymax>366</ymax>
		</bndbox>
	</object>
</annotation>
