<annotation>
	<folder>noenr</folder>
	<filename>001789.jpg</filename>
	<path>C:\Users\NEAR6\Desktop\noenr\001789.jpg</path>
	<source>
		<database>Unknown</database>
	</source>
	<size>
		<width>600</width>
		<height>400</height>
		<depth>3</depth>
	</size>
	<segmented>0</segmented>
	<object>
		<name>No_entry</name>
		<pose>Unspecified</pose>
		<truncated>0</truncated>
		<difficult>0</difficult>
		<bndbox>
			<xmin>347</xmin>
			<ymin>9</ymin>
			<xmax>472</xmax>
			<ymax>145</ymax>
		</bndbox>
	</object>
</annotation>
