<annotation>
	<folder>nutr</folder>
	<filename>002022.jpg</filename>
	<path>C:\Users\NEAR6\Desktop\nutr\002022.jpg</path>
	<source>
		<database>Unknown</database>
	</source>
	<size>
		<width>620</width>
		<height>349</height>
		<depth>3</depth>
	</size>
	<segmented>0</segmented>
	<object>
		<name>No_u_turn</name>
		<pose>Unspecified</pose>
		<truncated>0</truncated>
		<difficult>0</difficult>
		<bndbox>
			<xmin>106</xmin>
			<ymin>29</ymin>
			<xmax>293</xmax>
			<ymax>216</ymax>
		</bndbox>
	</object>
</annotation>
